es_testbed/__init__.py
es_testbed/_base.py
es_testbed/_plan.py
es_testbed/debug.py
es_testbed/defaults.py
es_testbed/es_api.py
es_testbed/exceptions.py
es_testbed/ilm.py
es_testbed/py.typed
es_testbed/utils.py
es_testbed/entities/__init__.py
es_testbed/entities/alias.py
es_testbed/entities/data_stream.py
es_testbed/entities/entity.py
es_testbed/entities/index.py
es_testbed/helpers/__init__.py
es_testbed/helpers/es_api.py
es_testbed/helpers/utils.py
es_testbed/mgrs/__init__.py
es_testbed/mgrs/component.py
es_testbed/mgrs/data_stream.py
es_testbed/mgrs/entity.py
es_testbed/mgrs/ilm.py
es_testbed/mgrs/index.py
es_testbed/mgrs/snapshot.py
es_testbed/mgrs/template.py
es_testbed/presets/__init__.py
es_testbed/presets/searchable_test/__init__.py
es_testbed/presets/searchable_test/buildlist.yml
es_testbed/presets/searchable_test/definitions.py
es_testbed/presets/searchable_test/functions.py
es_testbed/presets/searchable_test/mappings.json
es_testbed/presets/searchable_test/plan.yml
es_testbed/presets/searchable_test/scenarios.py
es_testbed/presets/searchable_test/settings.json
es_testbed-0.11.3.dist-info/METADATA
es_testbed-0.11.3.dist-info/WHEEL
es_testbed-0.11.3.dist-info/licenses/LICENSE
es_testbed-0.11.3.dist-info/RECORD
