Metadata-Version: 2.3
Name: es-testbed
Version: 0.11.3
Summary: Library to help with building and tearing down indices, data streams, repositories and snapshots
Project-URL: Documentation, https://github.com/untergeek/es-testbed#readme
Project-URL: Issues, https://github.com/untergeek/es-testbed/issues
Project-URL: Source, https://github.com/untergeek/es-testbed
Author-email: Aaron Mildenstein <aaron@mildensteins.com>
License: Apache-2.0
License-File: LICENSE
Keywords: datastream,elasticsearch,index,repository,snapshot,testing
Classifier: Intended Audience :: Developers
Classifier: Intended Audience :: System Administrators
Classifier: License :: OSI Approved :: Apache Software License
Classifier: Operating System :: OS Independent
Classifier: Programming Language :: Python
Classifier: Programming Language :: Python :: 3.8
Classifier: Programming Language :: Python :: 3.9
Classifier: Programming Language :: Python :: 3.10
Classifier: Programming Language :: Python :: 3.11
Classifier: Programming Language :: Python :: 3.12
Requires-Python: >=3.8
Requires-Dist: dotmap==1.3.30
Requires-Dist: es-client>=8.18.2
Requires-Dist: es-wait>=0.15.1
Requires-Dist: gitpython==3.1.43
Requires-Dist: tiered-debug==1.3.0
Provides-Extra: doc
Requires-Dist: furo>=2024.8.6; extra == 'doc'
Provides-Extra: test
Requires-Dist: mock; extra == 'test'
Requires-Dist: pytest-cov; extra == 'test'
Requires-Dist: pytest-dotenv; extra == 'test'
Requires-Dist: pytest>=7.2.1; extra == 'test'
Requires-Dist: requests; extra == 'test'
